address/__init__.py
address_so-0.0.2.dist-info/METADATA
address_so-0.0.2.dist-info/WHEEL
address_so-0.0.2.dist-info/top_level.txt
address_so-0.0.2.dist-info/RECORD
