Metadata-Version: 2.1
Name: address-so
Version: 0.0.2
Summary: A unified API for blockchain developers
Home-page: https://github.com/address-so/address-python-sdk
Author: Reznichenko Yaroslav
Author-email: y@address.so
License: MIT
Platform: UNKNOWN
Requires-Python: >=3.6
Requires-Dist: requests (>=2.20.0)
